reg_file.v
module register_file (
    input clk,              
    input reset,            
    input write_en,         
    input [1:0] addr_1,
    input [63:0] data_in,   
    output reg [63:0] data_out   
);    
reg[63:0] registers [0:3];
always @(*)
begin
	if (write_en)
	registers[addr_1] <= data_in;
end
always@(*)
begin
	data_out = registers[addr_1]; 
end
endmodule

tb_reg_file.v
module tb_register_file;
	reg clk;
	reg reset;
	reg write_en;
	reg [1:0] addr_1;
	reg [63:0] data_in;
	wire [63:0] data_out;

    
register_file register_file_inst (
	.clk			(clk),
	.reset			(reset),
	.write_en		(write_en),
	.addr_1			(addr_1),
	.data_in		(data_in),
	.data_out		(data_out)
    );
	
 
always@(posedge clk)
begin
	clk=0;
	forever #4 clk =~ clk;	
end


initial begin
$dumpfile("waveform.vcd");
$dumpvars(1,tb_register_file);
clk = 1;
reset = 1;
@(posedge clk)
reset = 0;

@(posedge clk)
write_en = 1;
addr_1 = 2'b00;
data_in = 64'd15;
#1;
$display("Data from register 0: %d", data_out);

@(posedge clk)
addr_1 = 2'b01;
data_in = 64'd20;
#1;
$display("Data from register 1: %d", data_out);

@(posedge clk)
addr_1 = 2'b10;
data_in = 64'd25;
#1;
$display("Data from register 2: %d", data_out);

@(posedge clk)
addr_1 = 2'b11;
data_in = 64'd30;
#1;
$display("Data from register 3: %d", data_out);
repeat(5) @(posedge clk);


//@(posedge clk)
//addr_1 = 2'b00;
//#1;
//$display("Data from register 0: %d", data_out);


/*
@(posedge clk)
addr_2 = 2'b01;
data_in = 64'd20;
@(posedge clk)
addr_2 = 2'b10;
data_in = 64'd25;
@(posedge clk)
addr_2 = 2'b11;
data_in = 64'd30;
repeat(20) @(posedge clk);
*/


@(posedge clk)
addr_1 = 2'b00;
data_in = 64'd50;
repeat(5) @(posedge clk);
$display("Data from register 0: %d", data_out);
repeat(2) @(posedge clk);

@(posedge clk)
addr_1 = 2'b01;
data_in = 64'd55;
repeat(5) @(posedge clk);
$display("Data from register 1: %d", data_out);
repeat(2) @(posedge clk);

@(posedge clk)
addr_1 = 2'b10;
data_in = 64'd60;
repeat(5) @(posedge clk);
$display("Data from register 2: %d", data_out);
repeat(2) @(posedge clk);

addr_1 = 2'b11;
data_in = 64'd65;
repeat(20) @(posedge clk);
$display("Data from register 3: %d", data_out);
@(posedge clk)
write_en = 0;
$finish;
end
endmodule

waveform.vcd
$date
	Tue Mar 04 13:23:26 2025
$end
$version
	Icarus Verilog
$end
$timescale
	1s
$end
$scope module tb_register_file $end
$var wire 64 ! data_out [63:0] $end
$var reg 2 " addr_1 [1:0] $end
$var reg 1 # clk $end
$var reg 64 $ data_in [63:0] $end
$var reg 1 % reset $end
$var reg 1 & write_en $end
$upscope $end
$enddefinitions $end
$comment Show the parameter values. $end
$dumpall
$end
#0
$dumpvars
x&
1%
bx $
0#
bx "
bx !
$end
#4
0%
1#
#8
0#
#12
b1111 !
b1111 $
b0 "
1&
1#
#16
0#
#20
b10100 !
b10100 $
b1 "
1#
#24
0#
#28
b11001 !
b11001 $
b10 "
1#
#32
0#
#36
b11110 !
b11110 $
b11 "
1#
#40
0#
#44
1#
#48
0#
#52
1#
#56
0#
#60
1#
#64
0#
#68
1#
#72
0#
#76
1#
#80
0#
#84
b110010 !
b110010 $
b0 "
1#
#88
0#
#92
1#
#96
0#
#100
1#
#104
0#
#108
1#
#112
0#
#116
1#
#120
0#
#124
1#
#128
0#
#132
1#
#136
0#
#140
1#
#144
0#
#148
b110111 !
b110111 $
b1 "
1#
#152
0#
#156
1#
#160
0#
#164
1#
#168
0#
#172
1#
#176
0#
#180
1#
#184
0#
#188
1#
#192
0#
#196
1#
#200
0#
#204
1#
#208
0#
#212
b111100 !
b111100 $
b10 "
1#
#216
0#
#220
1#
#224
0#
#228
1#
#232
0#
#236
1#
#240
0#
#244
1#
#248
0#
#252
1#
#256
0#
#260
1#
#264
0#
#268
b1000001 !
b1000001 $
b11 "
1#
